Products.BTreeFolder2-5.0-py3.11-nspkg.pth
Products/BTreeFolder2/BTreeFolder2.py
Products/BTreeFolder2/__init__.py
Products/BTreeFolder2/btreefolder2.gif
Products/BTreeFolder2/contents.dtml
Products/BTreeFolder2/folderAdd.dtml
Products/BTreeFolder2/tests/__init__.py
Products/BTreeFolder2/tests/testBTreeFolder2.py
Products.BTreeFolder2-5.0.dist-info/LICENSE.txt
Products.BTreeFolder2-5.0.dist-info/METADATA
Products.BTreeFolder2-5.0.dist-info/WHEEL
Products.BTreeFolder2-5.0.dist-info/namespace_packages.txt
Products.BTreeFolder2-5.0.dist-info/top_level.txt
Products.BTreeFolder2-5.0.dist-info/RECORD
