Metadata-Version: 2.1
Name: Products.BTreeFolder2
Version: 5.0
Summary: A BTree based implementation for Zope's OFS.
Home-page: https://github.com/zopefoundation/Products.BTreeFolder2
Author: Zope Foundation and Contributors
Author-email: zope-dev@zope.dev
License: ZPL 2.1
Classifier: Development Status :: 6 - Mature
Classifier: Environment :: Web Environment
Classifier: Framework :: Zope
Classifier: Framework :: Zope :: 5
Classifier: License :: OSI Approved :: Zope Public License
Classifier: Operating System :: OS Independent
Classifier: Programming Language :: Python
Classifier: Programming Language :: Python :: 3
Classifier: Programming Language :: Python :: 3.7
Classifier: Programming Language :: Python :: 3.8
Classifier: Programming Language :: Python :: 3.9
Classifier: Programming Language :: Python :: 3.10
Classifier: Programming Language :: Python :: 3.11
Classifier: Programming Language :: Python :: Implementation :: CPython
Requires-Python: >=3.7
License-File: LICENSE.txt
Requires-Dist: setuptools
Requires-Dist: AccessControl
Requires-Dist: Acquisition
Requires-Dist: BTrees
Requires-Dist: ExtensionClass (>=4.1a1)
Requires-Dist: Persistence
Requires-Dist: Zope2 (>=4.0a5)
Requires-Dist: zope.container
Requires-Dist: zope.event
Requires-Dist: zope.lifecycleevent
